Workbook

Sheet 1-Valor_Unitário_Economia
A1: Nº Contrato SGL | B1: RC | C1: Nº Contrato SAP | D1: Objeto Reduzido | E1: Situação | F1: Valor Original | G1: Valor em Vigor | I1: Economias 2025 | J1: Economias 2026 | K1: Economias Totais | L1: Valor Médio Unitário por Economia
A2: 00200/24-0000 | B2: 0011335815 | C2: 4600058390 | D2: Integra Tietê - Fase 1 - Pacote 13 - Guarulhos - Bacia TL-02 e TL-04, Córrego Itapegica e Córrego Guarulhos | E2: ANDAMENTO | F2: 194200000 | G2: 198084000 | I2: 5007 | J2: 24545 | K2: 29552 | L2: =F2/K2 -> 6571.4672
A3: 00201/24-0000 | B3: 0011335870 | C3: 4600058391 | D3: Integra Tietê - Fase 1 - Pacote 12 - Guarulhos - Bacia TL-08, Córrego Cocaia | E3: ANDAMENTO | F3: 1.744721e+08 | G3: 1.7796154e+08 | I3: 0 | J3: 54908 | K3: 54908 | L3: =F3/K3 -> 3177.5351
A4: 00268/24-0000 | B4: 0011338479 | C4: 4600058482 | D4: Integra Tietê - Fase 1 - Pacote 10C - Guarulhos - Bacia TL-10, Rio Baquirivu Guaçu, Sub-Bacia do Alto Cocho Velho | E4: ANDAMENTO | F4: 1.8522295e+08 | G4: 1.8892741e+08 | I4: 0 | J4: 35358 | K4: 35358 | L4: =F4/K4 -> 5238.5019
A5: 00272/24-0000 e 00277/24-0000 | B5: 0011338337 | C5: 4600058357 | D5: Integra Tietê - Fase 1 - Pacote 10B - Guarulhos - Bacia TL10, Sub-Bacia do Médio Cocho Velho | E5: ANDAMENTO | F5: =158385034.35+161807674.43 -> 3.2019271e+08 | G5: =161552735.03+165043827.91 -> 3.2659656e+08 | I5: 20000 | J5: 15823 | K5: 35823 | L5: =F5/K5 -> 8938.188
A6: 00273/24-0000 | B6: 0011338433 | C6: 4600058585 | D6: Integra Tietê - Fase 1 - Pacote 15AB - Guarulhos - Bacia TL-10, Sub-bacia do Baixo Baquirivu Guaçu | E6: ANDAMENTO | F6: 1.492826e+08 | G6: 1.5226826e+08 | I6: 3146 | J6: 2098 | K6: 5244 | L6: =F6/K6 -> 28467.316
A7: 00274/24-0000 | B7: 0011338439 | C7: 4600058299 | D7: Integra Tietê - Fase 1 - Pacote 10A - Guarulhos - Bacia TL10, Rio Baquirivu Guaçu, Sub-Bacia do Baixo Cocho Velho | E7: ANDAMENTO | F7: 57501876 | G7: 57501876 | I7: 7176 | J7: 0 | K7: 7176 | L7: =F7/K7 -> 8013.082
A8: 00276/24-0000 | B8: 0011338444 | C8: 4600058798 | D8: Integra Tietê - Fase 1 - Pacote 15C - Guarulhos - Bacia TL10 - Rio Baquirivu Guaçu, Sub-bacia do Córrego Invernada | E8: ANDAMENTO | F8: 1.3517228e+08 | G8: 1.3787572e+08 | I8: 2416 | J8: 1611 | K8: 4027 | L8: =F8/K8 -> 33566.496
A9: 00276/24-0000 | B9: 0011352094 | C9: 4600057707 | D9: Itaquaquecetuba - Coleta e Afastamento de Esgoto - Reversão da Bacia VI-03 - Coletores Félix, São Bento e outros | E9: ANDAMENTO | F9: 2.0173202e+08 | G9: 2.0173202e+08 | I9: 1040 | J9: 5779 | K9: 6819 | L9: =F9/K9 -> 29583.813
A10: 00721/24-0000 | B10: 0011354407 | C10: 4600058440 | D10: Integra Tietê - Fase 1 - Pacote 04A - São Paulo - Bacias TC-01, TC-03, TC-05, TC-07, TC-09, TC-11, TC-13, TC-13A, TC-15 E TC-17, Córregos Tatuapé, Pacaembu, Sumaré e Tiburtino | E10: ANDAMENTO | F10: 61262303 | G10: 61262303 | I10: 1222 | J10: 5991 | K10: 7213 | L10: =F10/K10 -> 8493.318
A11: 00722/24-0000 | B11: 0011354583 | C11: 4600058238 | D11: Integra Tietê - Fase 1 - Pacote 05A - Santo André e São Bernardo do Campo - Bacias ME-04, ME-05, ME-07 e ME-09, Baixo Ribeirão dos Meninos | E11: ANDAMENTO | F11: 57761768 | G11: 57761768 | I11: 3901 | J11: 5865 | K11: 9766 | L11: =F11/K11 -> 5914.5779
A12: 00723/24-0000 | B12: 0011354597 | C12: 4600058708 | D12: Integra Tietê - Fase 1 - Pacote 05C - São Bernardo do Campo - Bacias ME-10, ME-12, ME-13, ME-14, ME-15 e ME-17, Alto Ribeirão dos Meninos | E12: ANDAMENTO | F12: 60261143 | G12: 61466365 | I12: 20585 | J12: 21625 | K12: 42210 | L12: =F12/K12 -> 1427.6509
A13: 00725/24-0000 | B13: 0011354635 | C13: 4600058664 | D13: Integra Tietê - Fase 1 - Pacote 16 - Santo André - Bacias TA-23, TA-25, TA-27, TA-29 e TA-31, Margem Esquerda do Rio Tamanduateí | E13: ANDAMENTO | F13: 1.059332e+08 | G13: 1.059332e+08 | I13: 13260 | J13: 28105 | K13: 41365 | L13: =F13/K13 -> 2560.9381
A14: 00752/24-0000 | B14: 0011355328 | C14: 4600058487 | D14: Integra Tietê - Fase 1 - Pacote 02A - São Paulo - Bacias TC-14, TC-16, TC-18, TC-20, TC-22, TC-24 e TC-26, Córregos Mandaqui, Tenente Rocha, Carandiru e Mundo Novo | E14: ANDAMENTO | F14: 30467706 | G14: 30467706 | I14: 3655 | J14: 17919 | K14: 21574 | L14: =F14/K14 -> 1412.2419
A15: 00774/24-0000 | B15: 0011355672 | C15: 4600058240 | D15: Integra Tietê - Fase 1 - Pacote 05B - Santo André e São Bernardo do Campo - Bacias ME-06, ME-08 e ME-11, Médio Ribeirão Dos Meninos | E15: ANDAMENTO | F15: 1.3960116e+08 | G15: 1.4239319e+08 | I15: 21546 | J15: 28056 | K15: 49602 | L15: =F15/K15 -> 2814.4261
A16: 00797/24-0000 | B16: 0011357131 | C16: 4600058451 | D16: Integra Tietê - Fase 1 - Pacote 20 - Guarulhos e Arujá - Bacia TL-10, Margem Esquerda Do Alto Baquirivu-Guaçu | E16: ANDAMENTO | F16: 2.8363983e+08 | G16: 2.8931262e+08 | I16: 0 | J16: 20522 | K16: 20522 | L16: =F16/K16 -> 13821.257
A17: 00810/24-0000 | B17: 0011357802 | C17: 4600058993 | D17: Integra Tietê - Fase 1 - Pacote 18B - Barueri - Bacias TO-11 e TO-13, Rios São João do Barueri e Cotia | E17: ANDAMENTO | F17: 96134214 | G17: 96134214 | I17: 3908 | J17: 9936 | K17: 13844 | L17: =F17/K17 -> 6944.1068
... A42: 02502/24-0000 | B42: 0011416378 | C42: 4600058415 | D42: Integra Tietê - Fase 1 - Pacote 11 - Guarulhos - Bacia Tl-06, Ribeirão dos Cubas | E42: ANDAMENTO | F42: 1.759196e+08 | G42: 1.759196e+08 | I42: 0 | J42: 47744 | K42: 47744 | L42: =F42/K42 -> 3684.6432
L44: Valor Unitário por Economia
E46: TOTAL | F46: =SUM(F2:F42) -> 6.1583944e+09 | I46: =SUM(I2:I42) -> 263768 | J46: =SUM(J2:J42) -> 817823 | K46: =SUM(K2:K42) -> 1081591 | L46: =F46/K46 -> 5693.8291
A48: 00277/24-0000 | B48: 0011338456 | C48: 4600058530 | D48: Integra Tietê - Fase 1 - Pacote 15D - Guarulhos - Bacia TL10 - Rio Baquirivu Guaçu, Córrego Tanquinho | E48: ANDAMENTO | F48: 1.6180767e+08 | G48: 1.6504383e+08

Sheet 2-Proporção
B2: SERVIÇOS | C2: TOTAL M.O. | D2: TOTAL MAT. | E2: TOTAL EQUIP. | F2: TOTAL
B3: MND TUBO CRAVADO 300MM | C3: 64964878 | D3: 85909008 | E3: 2.2589603e+08 | F3: 3.7676992e+08
B4: MND TUBO CRAVADO 400MM | C4: 13587890 | D4: 24149628 | E4: 47310486 | F4: 85048004
B5: REDE ESG. 200MM | C5: 1.3408339e+08 | D5: 62647726 | E5: 39055414 | F5: 2.3578654e+08
B6: INT. 200MM | C6: 46486773 | D6: 21719200 | E6: 13408971 | F6: 81614945
B7: INT. COL. 300MM | C7: 30537417 | D7: 18090153 | E7: 10429617 | F7: 59057187
B8: TOTAL | C8: =SUM(C3:C7) -> 2.8966035e+08 | D8: =SUM(D3:D7) -> 2.1251572e+08 | E8: =SUM(E3:E7) -> 3.3610052e+08 | F8: =SUM(F3:F7) -> 8.3827659e+08
B9: % TOTAL | C9: =C8/$F$8 -> 0.3455427 | D9: =D8/$F$8 -> 0.25351503 | E9: =E8/$F$8 -> 0.40094227 | F9: 1

Sheet 3-Cenários
B2: Cenários - Mão de Obra
B4: Cenário A
B6: MO: uso da mão de obra prevista em contrato. Valor adicional considera o custo do dinheiro.
B8: Cenário B
B10: MO: uso da mão de obra prevista em contrato. Valor adicional considera o custo do dinheiro.
B11: MO: uso de mão de obra adicional, sob a forma de horas noturnas.
B13: Cenário C
B15: MO: uso da mão de obra prevista em contrato. Valor adicional considera o custo do dinheiro.
B16: MO: uso de mão de obra adicional, sob a forma de horas extras.
B18: Cenários - Materiais
B20: Cenário A
B22: Mat: uso dos materiais previstos em contrato. Valor adicional considera o custo do dinheiro.
... B46: Equip: uso de equipamentos adicionais, devido à garantir a produtividade do serviço antecipado.

Sheet 4-Premissas-MO
B2: CENÁRIO A - Fator Hora Normal
B3: Jornada | C3: Horas Semana | D3: Horas Diurnas na Semana | E3: Horas Noturnas na Semana | F3: Acréscimo %
B4: 44 semanais | C4: 44 | D4: - | E4: - | F4: -
B5: Custo Hora | C5: 1 | D5: - | E5: - | F5: =100%-1 -> 0
B7: CENÁRIO B - Fator Hora Noturna
B8: Jornada | C8: Horas Semana | D8: Horas Diurnas na Semana | E8: Horas Noturnas na Semana | F8: Acréscimo %
B9: 44 semanais | C9: 44 | D9: 9 | E9: 35 | F9: -
B10: Custo Hora | C10: 1 | D10: 1 | E10: =60/52.5*120% -> 1.3714286 | F10: =((D9*D10+E9*E10)/C9)-1 -> 0.29545455
B12: CENÁRIO C - Fator Hora Extra
B13: Jornada | C13: Horas Semana | D13: Limite Horas Extras na Semana | E13: Horas Extras Sábado | F13: Horas Extras Domingo | G13: Total Horas Semanais | H13: Acréscimo %
B14: 44 semanais | C14: 44 | D14: =(5*2) -> 10 | E14: 4 | G14: =SUM(C14:F14) -> 58 | H14: -
B15: Custo Hora | C15: 1 | D15: 1.5 | E15: 1.5 | F15: 2 | G15: =C14*C15+D14*D15+E14*E15+F14*+F15 -> 65 | H15: =(G15/C14)-1 -> 0.47727273

Sheet 5-Parâmetros
B1: Nº Contrato SGL: | C1: 00201/24-0000
B2: Parâmetros | C2: Dados
B3: Valor Total Contratado (2025 e 2026): | C3: =VLOOKUP(C1,'1-Valor_Unitário_Economia'!A1:F42,6,) -> 1.744721e+08
B4: Valor Contratado para 2026: | C4: =C5*VLOOKUP(C1,'1-Valor_Unitário_Economia'!A1:L42,12) -> 1.744721e+08
B5: Total de Economias 2026 do Integra Tietê: | C5: =VLOOKUP(C1,'1-Valor_Unitário_Economia'!A1:J42,10,) -> 54908
B6: % de Economia Antecipada: | C6: 0.1
B7: Economias a Antecipar do Contrato: | C7: =C6*C5 -> 5490.8
B8: Valor Original da Parcela do Serviço Antecipado: | C8: =VLOOKUP(C1,'1-Valor_Unitário_Economia'!A1:L42,12)*C7 -> 17447210
B9: Período Antecipado (em meses): | C9: 12
B10: Taxa Selic Anual: | C10: 0.15
B11: Aumento de Equipamentos - Cenário B | C11: 0.13
B12: Aumento de Equipamentos - Cenário C | C12: 0.13

Sheet 6-Custo_Oportunidade
B2: Descritivo | C2: Valor
B3: Parâmetros
B4: ='5-Parâmetros'!B9 -> Período Antecipado (em meses): | C4: ='5-Parâmetros'!C9 -> 12
B5: Taxa Mensal: | C5: =(1+'5-Parâmetros'!C10)^(1/12)-1 -> 0.011714917
B6: ='5-Parâmetros'!B8 -> Valor Original da Parcela do Serviço Antecipado: | C6: ='5-Parâmetros'!C8 -> 17447210
B7: Cálculo do Custo Financeiro Adicional para Custear a Antecipação
B8: Custo do Serviço Antecipado (Valor - BDI): | C8: =C6/128% -> 13630633
B9: Saldo do Custo Financeiro (juros): | C9: =-(FV(C5,C4,(C8/C4)))-C8 -> 913466.06

Sheet 7-Cálculo_Crashing
B2: Item de Custo | C2: Proporção Média | D2: Valor Rateio | E2: Cenário A | F2: Cenário B | G2: Cenário C
B3: Mão de Obra | C3: ='2-Proporção'!C9 -> 0.3455427 | D3: ='5-Parâmetros'!$C$8*'7-Cálculo_Crashing'!C3 -> 6028755.9 | E3: ='6-Custo_Oportunidade'!$C$9*'7-Cálculo_Crashing'!C3 -> 315641.53 | F3: =E3+(D3*('4-Premissas-MO'!F10)) -> 2096864.9 | G3: =E3+(D3*('4-Premissas-MO'!H15)) -> 3193002.3
B4: Materiais | C4: ='2-Proporção'!D9 -> 0.25351503 | D4: ='5-Parâmetros'!$C$8*'7-Cálculo_Crashing'!C4 -> 4423129.9 | E4: ='6-Custo_Oportunidade'!$C$9*'7-Cálculo_Crashing'!C4 -> 231577.38 | F4: =E4 -> 231577.38 | G4: =E4 -> 231577.38
B5: Equipamentos | C5: ='2-Proporção'!E9 -> 0.40094227 | D5: ='5-Parâmetros'!$C$8*'7-Cálculo_Crashing'!C5 -> 6995323.9 | E5: ='6-Custo_Oportunidade'!$C$9*'7-Cálculo_Crashing'!C5 -> 366247.16 | F5: =E5+(D5*'5-Parâmetros'!C11) -> 1275639.3 | G5: =E5+D5*'5-Parâmetros'!C12 -> 1275639.3
C6: Valor Adicional (A) | E6: =SUM(E3:E5) -> 913466.06 | F6: =SUM(F3:F5) -> 3604081.5 | G6: =SUM(G3:G5) -> 4700218.9
C7: Valor Original (O) | E7: ='5-Parâmetros'!$C$8 -> 17447210
C8: Valor Total (T = A + O) | E8: =E6+$E$7 -> 18360676 | F8: =F6+$E$7 -> 21051291 | G8: =G6+$E$7 -> 22147429
C9: Fator % de Aumento (T / O) | E9: =E8/$E$7-1 -> 0.052355997 | F9: =F8/$E$7-1 -> 0.20657065 | G9: =G8/$E$7-1 -> 0.2693966
C10: Valor Total Integra Tietê (VTIT) | E10: ='1-Valor_Unitário_Economia'!F46 -> 6.1583944e+09
C11: % de Aumento (A / VTIT) | E11: =E6/E10 -> 0.00014832861 | F11: =F6/E10 -> 0.00058523071 | G11: =G6/E10 -> 0.00076322149

Sheet 8-Simulação_A
B2: - Parâmetros Adotados na Análise:
D4: ='5-Parâmetros'!B3 -> Valor Total Contratado (2025 e 2026): | E4: ='5-Parâmetros'!C3 -> 1.744721e+08
D5: ='5-Parâmetros'!B4 -> Valor Contratado para 2026: | E5: ='5-Parâmetros'!C4 -> 1.744721e+08
D6: Pagamento Médio Mensal Contratado de 2026: | E6: =E5/E8 -> 14539341
D7: ='5-Parâmetros'!B5 -> Total de Economias 2026 do Integra Tietê: | E7: ='5-Parâmetros'!C5 -> 54908
D8: ='5-Parâmetros'!B9 -> Período Antecipado (em meses): | E8: 12
D9: ='5-Parâmetros'!B10 -> Taxa Selic Anual: | E9: ='5-Parâmetros'!C10 -> 0.15
D10: ='5-Parâmetros'!B11 -> Aumento de Equipamentos - Cenário B | E10: ='5-Parâmetros'!C11 -> 0.13
D11: ='5-Parâmetros'!B12 -> Aumento de Equipamentos - Cenário C | E11: ='5-Parâmetros'!C12 -> 0.13
B13: - Cálculo das Economias:
B15: Parcela Antecipada | D15: Cenário A | G15: Cenário B | J15: Cenário C
B16: % | C16: Valor | D16: Valor Adicional | E16: % Parcela Antecipada | F16: % Valor Total Contratado | G16: Valor Adicional | H16: % Parcela Antecipada | I16: % Total | J16: Valor Adicional | K16: % Parcela Antecipada | L16: % Total
B17: 0.01 | C17: =$E$5*B17 -> 1744721 | D17: =$C17*('7-Cálculo_Crashing'!$E$9) -> 91346.606 | E17: =D17/$C17 -> 0.052355997 | F17: =D17/$E$4 -> 0.00052355997 | G17: =$C17*('7-Cálculo_Crashing'!$F$9) -> 360408.15 | H17: =G17/$C17 -> 0.20657065 | I17: =G17/$E$4 -> 0.0020657065 | J17: =$C17*('7-Cálculo_Crashing'!$G$9) -> 470021.89 | K17: =J17/$C17 -> 0.2693966 | L17: =J17/$E$4 -> 0.002693966
B18: 0.02 | C18: =$E$5*B18 -> 3489441.9 | D18: =$C18*('7-Cálculo_Crashing'!$E$9) -> 182693.21 | E18: =D18/$C18 -> 0.052355997 | F18: =D18/$E$4 -> 0.0010471199 | G18: =$C18*('7-Cálculo_Crashing'!$F$9) -> 720816.3 | H18: =G18/$C18 -> 0.20657065 | I18: =G18/$E$4 -> 0.0041314131 | J18: =$C18*('7-Cálculo_Crashing'!$G$9) -> 940043.79 | K18: =J18/$C18 -> 0.2693966 | L18: =J18/$E$4 -> 0.005387932
B19: 0.03 | C19: =$E$5*B19 -> 5234162.9 | D19: =$C19*('7-Cálculo_Crashing'!$E$9) -> 274039.82 | E19: =D19/$C19 -> 0.052355997 | F19: =D19/$E$4 -> 0.0015706799 | G19: =$C19*('7-Cálculo_Crashing'!$F$9) -> 1081224.5 | H19: =G19/$C19 -> 0.20657065 | I19: =G19/$E$4 -> 0.0061971196 | J19: =$C19*('7-Cálculo_Crashing'!$G$9) -> 1410065.7 | K19: =J19/$C19 -> 0.2693966 | L19: =J19/$E$4 -> 0.0080818979
B20: 0.04 | C20: =$E$5*B20 -> 6978883.9 | D20: =$C20*('7-Cálculo_Crashing'!$E$9) -> 365386.42 | E20: =D20/$C20 -> 0.052355997 | F20: =D20/$E$4 -> 0.0020942399 | G20: =$C20*('7-Cálculo_Crashing'!$F$9) -> 1441632.6 | H20: =G20/$C20 -> 0.20657065 | I20: =G20/$E$4 -> 0.0082628261 | J20: =$C20*('7-Cálculo_Crashing'!$G$9) -> 1880087.6 | K20: =J20/$C20 -> 0.2693966 | L20: =J20/$E$4 -> 0.010775864
B21: 0.05 | C21: =$E$5*B21 -> 8723604.9 | D21: =$C21*('7-Cálculo_Crashing'!$E$9) -> 456733.03 | E21: =D21/$C21 -> 0.052355997 | F21: =D21/$E$4 -> 0.0026177999 | G21: =$C21*('7-Cálculo_Crashing'!$F$9) -> 1802040.8 | H21: =G21/$C21 -> 0.20657065 | I21: =G21/$E$4 -> 0.010328533 | J21: =$C21*('7-Cálculo_Crashing'!$G$9) -> 2350109.5 | K21: =J21/$C21 -> 0.2693966 | L21: =J21/$E$4 -> 0.01346983
B22: 0.06 | C22: =$E$5*B22 -> 10468326 | D22: =$C22*('7-Cálculo_Crashing'!$E$9) -> 548079.64 | E22: =D22/$C22 -> 0.052355997 | F22: =D22/$E$4 -> 0.0031413598 | G22: =$C22*('7-Cálculo_Crashing'!$F$9) -> 2162448.9 | H22: =G22/$C22 -> 0.20657065 | I22: =G22/$E$4 -> 0.012394239 | J22: =$C22*('7-Cálculo_Crashing'!$G$9) -> 2820131.4 | K22: =J22/$C22 -> 0.2693966 | L22: =J22/$E$4 -> 0.016163796
B23: 0.07 | C23: =$E$5*B23 -> 12213047 | D23: =$C23*('7-Cálculo_Crashing'!$E$9) -> 639426.24 | E23: =D23/$C23 -> 0.052355997 | F23: =D23/$E$4 -> 0.0036649198 | G23: =$C23*('7-Cálculo_Crashing'!$F$9) -> 2522857.1 | H23: =G23/$C23 -> 0.20657065 | I23: =G23/$E$4 -> 0.014459946 | J23: =$C23*('7-Cálculo_Crashing'!$G$9) -> 3290153.3 | K23: =J23/$C23 -> 0.2693966 | L23: =J23/$E$4 -> 0.018857762
B24: 0.08 | C24: =$E$5*B24 -> 13957768 | D24: =$C24*('7-Cálculo_Crashing'!$E$9) -> 730772.85 | E24: =D24/$C24 -> 0.052355997 | F24: =D24/$E$4 -> 0.0041884798 | G24: =$C24*('7-Cálculo_Crashing'!$F$9) -> 2883265.2 | H24: =G24/$C24 -> 0.20657065 | I24: =G24/$E$4 -> 0.016525652 | J24: =$C24*('7-Cálculo_Crashing'!$G$9) -> 3760175.2 | K24: =J24/$C24 -> 0.2693966 | L24: =J24/$E$4 -> 0.021551728
B25: 0.09 | C25: =$E$5*B25 -> 15702489 | D25: =$C25*('7-Cálculo_Crashing'!$E$9) -> 822119.46 | E25: =D25/$C25 -> 0.052355997 | F25: =D25/$E$4 -> 0.0047120397 | G25: =$C25*('7-Cálculo_Crashing'!$F$9) -> 3243673.4 | H25: =G25/$C25 -> 0.20657065 | I25: =G25/$E$4 -> 0.018591359 | J25: =$C25*('7-Cálculo_Crashing'!$G$9) -> 4230197 | K25: =J25/$C25 -> 0.2693966 | L25: =J25/$E$4 -> 0.024245694
B26: 0.1 | C26: =$E$5*B26 -> 17447210 | D26: =$C26*('7-Cálculo_Crashing'!$E$9) -> 913466.06 | E26: =D26/$C26 -> 0.052355997 | F26: =D26/$E$4 -> 0.0052355997 | G26: =$C26*('7-Cálculo_Crashing'!$F$9) -> 3604081.5 | H26: =G26/$C26 -> 0.20657065 | I26: =G26/$E$4 -> 0.020657065 | J26: =$C26*('7-Cálculo_Crashing'!$G$9) -> 4700218.9 | K26: =J26/$C26 -> 0.2693966 | L26: =J26/$E$4 -> 0.02693966
B27: 0.15 | C27: =$E$5*B27 -> 26170815 | D27: =$C27*('7-Cálculo_Crashing'!$E$9) -> 1370199.1 | E27: =D27/$C27 -> 0.052355997 | F27: =D27/$E$4 -> 0.0078533996 | G27: =$C27*('7-Cálculo_Crashing'!$F$9) -> 5406122.3 | H27: =G27/$C27 -> 0.20657065 | I27: =G27/$E$4 -> 0.030985598 | J27: =$C27*('7-Cálculo_Crashing'!$G$9) -> 7050328.4 | K27: =J27/$C27 -> 0.2693966 | L27: =J27/$E$4 -> 0.04040949
B28: 0.2 | C28: =$E$5*B28 -> 34894419 | D28: =$C28*('7-Cálculo_Crashing'!$E$9) -> 1826932.1 | E28: =D28/$C28 -> 0.052355997 | F28: =D28/$E$4 -> 0.010471199 | G28: =$C28*('7-Cálculo_Crashing'!$F$9) -> 7208163 | H28: =G28/$C28 -> 0.20657065 | I28: =G28/$E$4 -> 0.041314131 | J28: =$C28*('7-Cálculo_Crashing'!$G$9) -> 9400437.9 | K28: =J28/$C28 -> 0.2693966 | L28: =J28/$E$4 -> 0.05387932
... B37: 1 | C37: =$E$5*B37 -> 1.744721e+08 | D37: =$C37*('7-Cálculo_Crashing'!$E$9) -> 9134660.6 | E37: =D37/$C37 -> 0.052355997 | F37: =D37/$E$4 -> 0.052355997 | G37: =$C37*('7-Cálculo_Crashing'!$F$9) -> 36040815 | H37: =G37/$C37 -> 0.20657065 | I37: =G37/$E$4 -> 0.20657065 | J37: =$C37*('7-Cálculo_Crashing'!$G$9) -> 47002189 | K37: =J37/$C37 -> 0.2693966 | L37: =J37/$E$4 -> 0.2693966

Sheet 9-Comparação
B2: - Comparações dos Contratos nos Cenários A, B e C
B4: % Parcela Antecipada: | C4: 0.1
B6: Contrato | F6: Cenário A | I6: Cenário B | L6: Cenário C
B7: Nº Contrato SGL | C7: Valor Total Contratado (2025/2026) | D7: Valor Contratado para 2026 | E7: Valor | F7: Valor Adicional | G7: % Parcela Antecipada | H7: % Valor Total Contratado | I7: Valor Adicional | J7: % Parcela Antecipada | K7: % Total | L7: Valor Adicional | M7: % Parcela Antecipada | N7: % Total
B8: 00200/24-0000 | C8: =VLOOKUP(B8,'1-Valor_Unitário_Economia'!$A$1:$F$42,6,) -> 194200000 | D8: =VLOOKUP(B8,'1-Valor_Unitário_Economia'!$A$1:$J$42,10,)*VLOOKUP(B8,'1-Valor_Unitário_Economia'!$A$1:$L$42,12) -> 1.6129666e+08 | E8: =D8*$C$4 -> 16129666 | F8: =E8*'7-Cálculo_Crashing'!$E$9 -> 844484.76 | G8: =IF(AND(ISNUMBER(E8), ISNUMBER(F8), E8>0, F8>0), F8/E8, 0) -> 0.052355997 | H8: =F8/C8 -> 0.0043485312 | I8: =E8*'7-Cálculo_Crashing'!$F$9 -> 3331915.7 | J8: =IF(AND(ISNUMBER(E8), ISNUMBER(I8), E8>0, I8>0), I8/E8, 0) -> 0.20657065 | K8: =I8/C8 -> 0.017157135 | L8: =E8*'7-Cálculo_Crashing'!$G$9 -> 4345277.2 | M8: =IF(AND(ISNUMBER(E8), ISNUMBER(L8), E8>0, L8>0), L8/E8, 0) -> 0.2693966 | N8: =L8/C8 -> 0.022375269
B9: 00201/24-0000 | C9: =VLOOKUP(B9,'1-Valor_Unitário_Economia'!$A$1:$F$42,6,) -> 1.744721e+08 | D9: =VLOOKUP(B9,'1-Valor_Unitário_Economia'!$A$1:$J$42,10,)*VLOOKUP(B9,'1-Valor_Unitário_Economia'!$A$1:$L$42,12) -> 1.744721e+08 | E9: =D9*$C$4 -> 17447210 | F9: =E9*'7-Cálculo_Crashing'!$E$9 -> 913466.06 | G9: =IF(AND(ISNUMBER(E9), ISNUMBER(F9), E9>0, F9>0), F9/E9, 0) -> 0.052355997 | H9: =F9/C9 -> 0.0052355997 | I9: =E9*'7-Cálculo_Crashing'!$F$9 -> 3604081.5 | J9: =IF(AND(ISNUMBER(E9), ISNUMBER(I9), E9>0, I9>0), I9/E9, 0) -> 0.20657065 | K9: =I9/C9 -> 0.020657065 | L9: =E9*'7-Cálculo_Crashing'!$G$9 -> 4700218.9 | M9: =IF(AND(ISNUMBER(E9), ISNUMBER(L9), E9>0, L9>0), L9/E9, 0) -> 0.2693966 | N9: =L9/C9 -> 0.02693966
B10: 00268/24-0000 | C10: =VLOOKUP(B10,'1-Valor_Unitário_Economia'!$A$1:$F$42,6,) -> 1.8522295e+08 | D10: =VLOOKUP(B10,'1-Valor_Unitário_Economia'!$A$1:$J$42,10,)*VLOOKUP(B10,'1-Valor_Unitário_Economia'!$A$1:$L$42,12) -> 1.8522295e+08 | E10: =D10*$C$4 -> 18522295 | F10: =E10*'7-Cálculo_Crashing'!$E$9 -> 969753.23 | G10: =IF(AND(ISNUMBER(E10), ISNUMBER(F10), E10>0, F10>0), F10/E10, 0) -> 0.052355997 | H10: =F10/C10 -> 0.0052355997 | I10: =E10*'7-Cálculo_Crashing'!$F$9 -> 3826162.6 | J10: =IF(AND(ISNUMBER(E10), ISNUMBER(I10), E10>0, I10>0), I10/E10, 0) -> 0.20657065 | K10: =I10/C10 -> 0.020657065 | L10: =E10*'7-Cálculo_Crashing'!$G$9 -> 4989843.3 | M10: =IF(AND(ISNUMBER(E10), ISNUMBER(L10), E10>0, L10>0), L10/E10, 0) -> 0.2693966 | N10: =L10/C10 -> 0.02693966
B11: 00272/24-0000 e 00277/24-0000 | C11: =VLOOKUP(B11,'1-Valor_Unitário_Economia'!$A$1:$F$42,6,) -> 3.2019271e+08 | D11: =VLOOKUP(B11,'1-Valor_Unitário_Economia'!$A$1:$J$42,10,)*VLOOKUP(B11,'1-Valor_Unitário_Economia'!$A$1:$L$42,12) -> 1.4142895e+08 | E11: =D11*$C$4 -> 14142895 | F11: =E11*'7-Cálculo_Crashing'!$E$9 -> 740465.36 | G11: =IF(AND(ISNUMBER(E11), ISNUMBER(F11), E11>0, F11>0), F11/E11, 0) -> 0.052355997 | H11: =F11/C11 -> 0.0023125616 | I11: =E11*'7-Cálculo_Crashing'!$F$9 -> 2921507 | J11: =IF(AND(ISNUMBER(E11), ISNUMBER(I11), E11>0, I11>0), I11/E11, 0) -> 0.20657065 | K11: =I11/C11 -> 0.0091242147 | L11: =E11*'7-Cálculo_Crashing'!$G$9 -> 3810047.8 | M11: =IF(AND(ISNUMBER(E11), ISNUMBER(L11), E11>0, L11>0), L11/E11, 0) -> 0.2693966 | N11: =L11/C11 -> 0.011899233
B12: 00273/24-0000 | C12: =VLOOKUP(B12,'1-Valor_Unitário_Economia'!$A$1:$F$42,6,) -> 1.492826e+08 | D12: =VLOOKUP(B12,'1-Valor_Unitário_Economia'!$A$1:$J$42,10,)*VLOOKUP(B12,'1-Valor_Unitário_Economia'!$A$1:$L$42,12) -> 59724429 | E12: =D12*$C$4 -> 5972442.9 | F12: =E12*'7-Cálculo_Crashing'!$E$9 -> 312693.2 | G12: =IF(AND(ISNUMBER(E12), ISNUMBER(F12), E12>0, F12>0), F12/E12, 0) -> 0.052355997 | H12: =F12/C12 -> 0.0020946392 | I12: =E12*'7-Cálculo_Crashing'!$F$9 -> 1233731.4 | J12: =IF(AND(ISNUMBER(E12), ISNUMBER(I12), E12>0, I12>0), I12/E12, 0) -> 0.20657065 | K12: =I12/C12 -> 0.0082644018 | L12: =E12*'7-Cálculo_Crashing'!$G$9 -> 1608955.8 | M12: =IF(AND(ISNUMBER(E12), ISNUMBER(L12), E12>0, L12>0), L12/E12, 0) -> 0.2693966 | N12: =L12/C12 -> 0.010777919
B13: 00274/24-0000 | C13: =VLOOKUP(B13,'1-Valor_Unitário_Economia'!$A$1:$F$42,6,) -> 57501876 | D13: =VLOOKUP(B13,'1-Valor_Unitário_Economia'!$A$1:$J$42,10,)*VLOOKUP(B13,'1-Valor_Unitário_Economia'!$A$1:$L$42,12) -> 0 | E13: =D13*$C$4 -> 0 | F13: =E13*'7-Cálculo_Crashing'!$E$9 -> 0 | G13: =IF(AND(ISNUMBER(E13), ISNUMBER(F13), E13>0, F13>0), F13/E13, 0) -> 0 | H13: =F13/C13 -> 0 | I13: =E13*'7-Cálculo_Crashing'!$F$9 -> 0 | J13: =IF(AND(ISNUMBER(E13), ISNUMBER(I13), E13>0, I13>0), I13/E13, 0) -> 0 | K13: =I13/C13 -> 0 | L13: =E13*'7-Cálculo_Crashing'!$G$9 -> 0 | M13: =IF(AND(ISNUMBER(E13), ISNUMBER(L13), E13>0, L13>0), L13/E13, 0) -> 0 | N13: =L13/C13 -> 0
B14: 00276/24-0000 | C14: =VLOOKUP(B14,'1-Valor_Unitário_Economia'!$A$1:$F$42,6,) -> 1.3517228e+08 | D14: =VLOOKUP(B14,'1-Valor_Unitário_Economia'!$A$1:$J$42,10,)*VLOOKUP(B14,'1-Valor_Unitário_Economia'!$A$1:$L$42,12) -> 47659523 | E14: =D14*$C$4 -> 4765952.3 | F14: =E14*'7-Cálculo_Crashing'!$E$9 -> 249526.19 | G14: =IF(AND(ISNUMBER(E14), ISNUMBER(F14), E14>0, F14>0), F14/E14, 0) -> 0.052355997 | H14: =F14/C14 -> 0.0018459864 | I14: =E14*'7-Cálculo_Crashing'!$F$9 -> 984505.89 | J14: =IF(AND(ISNUMBER(E14), ISNUMBER(I14), E14>0, I14>0), I14/E14, 0) -> 0.20657065 | K14: =I14/C14 -> 0.0072833417 | L14: =E14*'7-Cálculo_Crashing'!$G$9 -> 1283931.3 | M14: =IF(AND(ISNUMBER(E14), ISNUMBER(L14), E14>0, L14>0), L14/E14, 0) -> 0.2693966 | N14: =L14/C14 -> 0.0094984813
B15: 00636/24-0000 | C15: =VLOOKUP(B15,'1-Valor_Unitário_Economia'!$A$1:$F$42,6,) -> #N/A | D15: =VLOOKUP(B15,'1-Valor_Unitário_Economia'!$A$1:$J$42,10,)*VLOOKUP(B15,'1-Valor_Unitário_Economia'!$A$1:$L$42,12) -> #N/A | E15: =D15*$C$4 -> #N/A | F15: =E15*'7-Cálculo_Crashing'!$E$9 -> #N/A | G15: =IF(AND(ISNUMBER(E15), ISNUMBER(F15), E15>0, F15>0), F15/E15, 0) -> #N/A | H15: =F15/C15 -> #N/A | I15: =E15*'7-Cálculo_Crashing'!$F$9 -> #N/A | J15: =IF(AND(ISNUMBER(E15), ISNUMBER(I15), E15>0, I15>0), I15/E15, 0) -> #N/A | K15: =I15/C15 -> #N/A | L15: =E15*'7-Cálculo_Crashing'!$G$9 -> #N/A | M15: =IF(AND(ISNUMBER(E15), ISNUMBER(L15), E15>0, L15>0), L15/E15, 0) -> #N/A | N15: =L15/C15 -> #N/A
B16: 00721/24-0000 | C16: =VLOOKUP(B16,'1-Valor_Unitário_Economia'!$A$1:$F$42,6,) -> 61262303 | D16: =VLOOKUP(B16,'1-Valor_Unitário_Economia'!$A$1:$J$42,10,)*VLOOKUP(B16,'1-Valor_Unitário_Economia'!$A$1:$L$42,12) -> 50883468 | E16: =D16*$C$4 -> 5088346.8 | F16: =E16*'7-Cálculo_Crashing'!$E$9 -> 266405.47 | G16: =IF(AND(ISNUMBER(E16), ISNUMBER(F16), E16>0, F16>0), F16/E16, 0) -> 0.052355997 | H16: =F16/C16 -> 0.0043486036 | I16: =E16*'7-Cálculo_Crashing'!$F$9 -> 1051103.1 | J16: =IF(AND(ISNUMBER(E16), ISNUMBER(I16), E16>0, I16>0), I16/E16, 0) -> 0.20657065 | K16: =I16/C16 -> 0.017157421 | L16: =E16*'7-Cálculo_Crashing'!$G$9 -> 1370783.3 | M16: =IF(AND(ISNUMBER(E16), ISNUMBER(L16), E16>0, L16>0), L16/E16, 0) -> 0.2693966 | N16: =L16/C16 -> 0.022375641
B17: 00722/24-0000 | C17: =VLOOKUP(B17,'1-Valor_Unitário_Economia'!$A$1:$F$42,6,) -> 57761768 | D17: =VLOOKUP(B17,'1-Valor_Unitário_Economia'!$A$1:$J$42,10,)*VLOOKUP(B17,'1-Valor_Unitário_Economia'!$A$1:$L$42,12) -> 34688999 | E17: =D17*$C$4 -> 3468899.9 | F17: =E17*'7-Cálculo_Crashing'!$E$9 -> 181617.71 | G17: =IF(AND(ISNUMBER(E17), ISNUMBER(F17), E17>0, F17>0), F17/E17, 0) -> 0.052355997 | H17: =F17/C17 -> 0.0031442548 | I17: =E17*'7-Cálculo_Crashing'!$F$9 -> 716572.92 | J17: =IF(AND(ISNUMBER(E17), ISNUMBER(I17), E17>0, I17>0), I17/E17, 0) -> 0.20657065 | K17: =I17/C17 -> 0.012405661 | L17: =E17*'7-Cálculo_Crashing'!$G$9 -> 934509.84 | M17: =IF(AND(ISNUMBER(E17), ISNUMBER(L17), E17>0, L17>0), L17/E17, 0) -> 0.2693966 | N17: =L17/C17 -> 0.016178692
B18: 00723/24-0000 | C18: =VLOOKUP(B18,'1-Valor_Unitário_Economia'!$A$1:$F$42,6,) -> 60261143 | D18: =VLOOKUP(B18,'1-Valor_Unitário_Economia'!$A$1:$J$42,10,)*VLOOKUP(B18,'1-Valor_Unitário_Economia'!$A$1:$L$42,12) -> 30872950 | E18: =D18*$C$4 -> 3087295 | F18: =E18*'7-Cálculo_Crashing'!$E$9 -> 161638.41 | G18: =IF(AND(ISNUMBER(E18), ISNUMBER(F18), E18>0, F18>0), F18/E18, 0) -> 0.052355997 | H18: =F18/C18 -> 0.0026822991 | I18: =E18*'7-Cálculo_Crashing'!$F$9 -> 637744.54 | J18: =IF(AND(ISNUMBER(E18), ISNUMBER(I18), E18>0, I18>0), I18/E18, 0) -> 0.20657065 | K18: =I18/C18 -> 0.010583014 | L18: =E18*'7-Cálculo_Crashing'!$G$9 -> 831706.76 | M18: =IF(AND(ISNUMBER(E18), ISNUMBER(L18), E18>0, L18>0), L18/E18, 0) -> 0.2693966 | N18: =L18/C18 -> 0.013801709
B19: 00725/24-0000 | C19: =VLOOKUP(B19,'1-Valor_Unitário_Economia'!$A$1:$F$42,6,) -> 1.059332e+08 | D19: =VLOOKUP(B19,'1-Valor_Unitário_Economia'!$A$1:$J$42,10,)*VLOOKUP(B19,'1-Valor_Unitário_Economia'!$A$1:$L$42,12) -> 71975164 | E19: =D19*$C$4 -> 7197516.4 | F19: =E19*'7-Cálculo_Crashing'!$E$9 -> 376833.15 | G19: =IF(AND(ISNUMBER(E19), ISNUMBER(F19), E19>0, F19>0), F19/E19, 0) -> 0.052355997 | H19: =F19/C19 -> 0.0035572714 | I19: =E19*'7-Cálculo_Crashing'!$F$9 -> 1486795.7 | J19: =IF(AND(ISNUMBER(E19), ISNUMBER(I19), E19>0, I19>0), I19/E19, 0) -> 0.20657065 | K19: =I19/C19 -> 0.014035219 | L19: =E19*'7-Cálculo_Crashing'!$G$9 -> 1938986.4 | M19: =IF(AND(ISNUMBER(E19), ISNUMBER(L19), E19>0, L19>0), L19/E19, 0) -> 0.2693966 | N19: =L19/C19 -> 0.018303859
... B48: 02502/24-0000 | C48: =VLOOKUP(B48,'1-Valor_Unitário_Economia'!$A$1:$F$42,6,) -> 1.759196e+08 | D48: =VLOOKUP(B48,'1-Valor_Unitário_Economia'!$A$1:$J$42,10,)*VLOOKUP(B48,'1-Valor_Unitário_Economia'!$A$1:$L$42,12) -> 1.759196e+08 | E48: =D48*$C$4 -> 17591960 | F48: =E48*'7-Cálculo_Crashing'!$E$9 -> 921044.63 | G48: =IF(AND(ISNUMBER(E48), ISNUMBER(F48), E48>0, F48>0), F48/E48, 0) -> 0.052355997 | H48: =F48/C48 -> 0.0052355997 | I48: =E48*'7-Cálculo_Crashing'!$F$9 -> 3633982.7 | J48: =IF(AND(ISNUMBER(E48), ISNUMBER(I48), E48>0, I48>0), I48/E48, 0) -> 0.20657065 | K48: =I48/C48 -> 0.020657065 | L48: =E48*'7-Cálculo_Crashing'!$G$9 -> 4739214.3 | M48: =IF(AND(ISNUMBER(E48), ISNUMBER(L48), E48>0, L48>0), L48/E48, 0) -> 0.2693966 | N48: =L48/C48 -> 0.02693966
